[{
  "_id": {
    "$oid": "637e96e0f4f8575044eb39d9"
  },
  "firstName": "Sharare",
  "lastName": "Norouzi",
  "email": "sharare@gmail.com",
  "password": "$2b$10$9gOKMffHSGJqReHZkNSeGO69hwuIOlczlj4FU0RpvXlXPM6alRwUu"
},{
  "_id": {
    "$oid": "637fa587bfb2abdbad9d34b5"
  },
  "firstName": "Hanieh",
  "lastName": "Sotudeh",
  "email": "hanie@gmail.com",
  "password": "$2b$10$3gQVjAXpjkBixbTS73e.5Orp749OKSf0NiySIBGHNPf7jsJQSrEsW"
},{
  "_id": {
    "$oid": "63857ea362324846aa1f5ddc"
  },
  "firstName": "Sharare",
  "lastName": "Norouzi",
  "email": "norouzi.sharare@gmail.com",
  "password": "$2b$10$I81D5IwpYAVkltL..1icSedSPZ6XzGB/V/6j3S6hunST5STz8duq6",
  "__v": 0
}]